[{"name":"BOTTOM_UP","description":"ktfio.FileWalkDirection.BOTTOM_UP","location":"ktfio/ktfio/-file-walk-direction/-b-o-t-t-o-m_-u-p/index.html","searchKeys":["BOTTOM_UP","BOTTOM_UP","ktfio.FileWalkDirection.BOTTOM_UP"]},{"name":"TOP_DOWN","description":"ktfio.FileWalkDirection.TOP_DOWN","location":"ktfio/ktfio/-file-walk-direction/-t-o-p_-d-o-w-n/index.html","searchKeys":["TOP_DOWN","TOP_DOWN","ktfio.FileWalkDirection.TOP_DOWN"]},{"name":"class FileNotFoundException(fileName: String, reason: String) : FileIOException","description":"ktfio.FileNotFoundException","location":"ktfio/ktfio/-file-not-found-exception/index.html","searchKeys":["FileNotFoundException","class FileNotFoundException(fileName: String, reason: String) : FileIOException","ktfio.FileNotFoundException"]},{"name":"class FileTreeWalk : Sequence<File> ","description":"ktfio.FileTreeWalk","location":"ktfio/ktfio/-file-tree-walk/index.html","searchKeys":["FileTreeWalk","class FileTreeWalk : Sequence<File> ","ktfio.FileTreeWalk"]},{"name":"class IllegalFileAccess(fileName: String, reason: String) : FileIOException","description":"ktfio.IllegalFileAccess","location":"ktfio/ktfio/-illegal-file-access/index.html","searchKeys":["IllegalFileAccess","class IllegalFileAccess(fileName: String, reason: String) : FileIOException","ktfio.IllegalFileAccess"]},{"name":"enum FileWalkDirection : Enum<FileWalkDirection> ","description":"ktfio.FileWalkDirection","location":"ktfio/ktfio/-file-walk-direction/index.html","searchKeys":["FileWalkDirection","enum FileWalkDirection : Enum<FileWalkDirection> ","ktfio.FileWalkDirection"]},{"name":"expect class File","description":"ktfio.File","location":"ktfio/ktfio/-file/index.html","searchKeys":["File","expect class File","ktfio.File"]},{"name":"expect fun File(pathname: String)","description":"ktfio.File.File","location":"ktfio/ktfio/-file/-file.html","searchKeys":["File","expect fun File(pathname: String)","ktfio.File.File"]},{"name":"expect fun File.appendText(text: String)","description":"ktfio.appendText","location":"ktfio/ktfio/append-text.html","searchKeys":["appendText","expect fun File.appendText(text: String)","ktfio.appendText"]},{"name":"expect fun File.readBytes(): ByteArray","description":"ktfio.readBytes","location":"ktfio/ktfio/read-bytes.html","searchKeys":["readBytes","expect fun File.readBytes(): ByteArray","ktfio.readBytes"]},{"name":"expect fun File.readText(): String","description":"ktfio.readText","location":"ktfio/ktfio/read-text.html","searchKeys":["readText","expect fun File.readText(): String","ktfio.readText"]},{"name":"expect fun File.writeBytes(bytes: ByteArray)","description":"ktfio.writeBytes","location":"ktfio/ktfio/write-bytes.html","searchKeys":["writeBytes","expect fun File.writeBytes(bytes: ByteArray)","ktfio.writeBytes"]},{"name":"expect fun File.writeText(text: String)","description":"ktfio.writeText","location":"ktfio/ktfio/write-text.html","searchKeys":["writeText","expect fun File.writeText(text: String)","ktfio.writeText"]},{"name":"expect fun canRead(): Boolean","description":"ktfio.File.canRead","location":"ktfio/ktfio/-file/can-read.html","searchKeys":["canRead","expect fun canRead(): Boolean","ktfio.File.canRead"]},{"name":"expect fun canWrite(): Boolean","description":"ktfio.File.canWrite","location":"ktfio/ktfio/-file/can-write.html","searchKeys":["canWrite","expect fun canWrite(): Boolean","ktfio.File.canWrite"]},{"name":"expect fun createNewFile(): Boolean","description":"ktfio.File.createNewFile","location":"ktfio/ktfio/-file/create-new-file.html","searchKeys":["createNewFile","expect fun createNewFile(): Boolean","ktfio.File.createNewFile"]},{"name":"expect fun delete(): Boolean","description":"ktfio.File.delete","location":"ktfio/ktfio/-file/delete.html","searchKeys":["delete","expect fun delete(): Boolean","ktfio.File.delete"]},{"name":"expect fun exists(): Boolean","description":"ktfio.File.exists","location":"ktfio/ktfio/-file/exists.html","searchKeys":["exists","expect fun exists(): Boolean","ktfio.File.exists"]},{"name":"expect fun getAbsolutePath(): String","description":"ktfio.File.getAbsolutePath","location":"ktfio/ktfio/-file/get-absolute-path.html","searchKeys":["getAbsolutePath","expect fun getAbsolutePath(): String","ktfio.File.getAbsolutePath"]},{"name":"expect fun getName(): String","description":"ktfio.File.getName","location":"ktfio/ktfio/-file/get-name.html","searchKeys":["getName","expect fun getName(): String","ktfio.File.getName"]},{"name":"expect fun getParent(): String?","description":"ktfio.File.getParent","location":"ktfio/ktfio/-file/get-parent.html","searchKeys":["getParent","expect fun getParent(): String?","ktfio.File.getParent"]},{"name":"expect fun getParentFile(): File?","description":"ktfio.File.getParentFile","location":"ktfio/ktfio/-file/get-parent-file.html","searchKeys":["getParentFile","expect fun getParentFile(): File?","ktfio.File.getParentFile"]},{"name":"expect fun isDirectory(): Boolean","description":"ktfio.File.isDirectory","location":"ktfio/ktfio/-file/is-directory.html","searchKeys":["isDirectory","expect fun isDirectory(): Boolean","ktfio.File.isDirectory"]},{"name":"expect fun isFile(): Boolean","description":"ktfio.File.isFile","location":"ktfio/ktfio/-file/is-file.html","searchKeys":["isFile","expect fun isFile(): Boolean","ktfio.File.isFile"]},{"name":"expect fun lastModified(): Long","description":"ktfio.File.lastModified","location":"ktfio/ktfio/-file/last-modified.html","searchKeys":["lastModified","expect fun lastModified(): Long","ktfio.File.lastModified"]},{"name":"expect fun list(): Array<String>","description":"ktfio.File.list","location":"ktfio/ktfio/-file/list.html","searchKeys":["list","expect fun list(): Array<String>","ktfio.File.list"]},{"name":"expect fun listFiles(): Array<File>","description":"ktfio.File.listFiles","location":"ktfio/ktfio/-file/list-files.html","searchKeys":["listFiles","expect fun listFiles(): Array<File>","ktfio.File.listFiles"]},{"name":"expect fun mkdirs(): Boolean","description":"ktfio.File.mkdirs","location":"ktfio/ktfio/-file/mkdirs.html","searchKeys":["mkdirs","expect fun mkdirs(): Boolean","ktfio.File.mkdirs"]},{"name":"expect val File.mimeType: String","description":"ktfio.mimeType","location":"ktfio/ktfio/mime-type.html","searchKeys":["mimeType","expect val File.mimeType: String","ktfio.mimeType"]},{"name":"expect val filePathSeparator: Char","description":"ktfio.filePathSeparator","location":"ktfio/ktfio/file-path-separator.html","searchKeys":["filePathSeparator","expect val filePathSeparator: Char","ktfio.filePathSeparator"]},{"name":"fun File(jsfile: File)","description":"ktfio.File.File","location":"ktfio/ktfio/-file/-file.html","searchKeys":["File","fun File(jsfile: File)","ktfio.File.File"]},{"name":"fun File.asParent(child: String): File","description":"ktfio.asParent","location":"ktfio/ktfio/as-parent.html","searchKeys":["asParent","fun File.asParent(child: String): File","ktfio.asParent"]},{"name":"fun File.copyTo(dest: File, overwrite: Boolean)","description":"ktfio.copyTo","location":"ktfio/ktfio/copy-to.html","searchKeys":["copyTo","fun File.copyTo(dest: File, overwrite: Boolean)","ktfio.copyTo"]},{"name":"fun File.copyTo(dest: String, overwrite: Boolean)","description":"ktfio.copyTo","location":"ktfio/ktfio/copy-to.html","searchKeys":["copyTo","fun File.copyTo(dest: String, overwrite: Boolean)","ktfio.copyTo"]},{"name":"fun File.deleteRecursively(): Boolean","description":"ktfio.deleteRecursively","location":"ktfio/ktfio/delete-recursively.html","searchKeys":["deleteRecursively","fun File.deleteRecursively(): Boolean","ktfio.deleteRecursively"]},{"name":"fun File.getParentFileUnsafe(): File","description":"ktfio.getParentFileUnsafe","location":"ktfio/ktfio/get-parent-file-unsafe.html","searchKeys":["getParentFileUnsafe","fun File.getParentFileUnsafe(): File","ktfio.getParentFileUnsafe"]},{"name":"fun File.moveTo(dest: File, overwrite: Boolean)","description":"ktfio.moveTo","location":"ktfio/ktfio/move-to.html","searchKeys":["moveTo","fun File.moveTo(dest: File, overwrite: Boolean)","ktfio.moveTo"]},{"name":"fun File.moveTo(dest: String, overwrite: Boolean)","description":"ktfio.moveTo","location":"ktfio/ktfio/move-to.html","searchKeys":["moveTo","fun File.moveTo(dest: String, overwrite: Boolean)","ktfio.moveTo"]},{"name":"fun File.validate()","description":"ktfio.validate","location":"ktfio/ktfio/validate.html","searchKeys":["validate","fun File.validate()","ktfio.validate"]},{"name":"fun File.walk(direction: FileWalkDirection = FileWalkDirection.TOP_DOWN): FileTreeWalk","description":"ktfio.walk","location":"ktfio/ktfio/walk.html","searchKeys":["walk","fun File.walk(direction: FileWalkDirection = FileWalkDirection.TOP_DOWN): FileTreeWalk","ktfio.walk"]},{"name":"fun File.walkBottomUp(): FileTreeWalk","description":"ktfio.walkBottomUp","location":"ktfio/ktfio/walk-bottom-up.html","searchKeys":["walkBottomUp","fun File.walkBottomUp(): FileTreeWalk","ktfio.walkBottomUp"]},{"name":"fun File.walkTopDown(): FileTreeWalk","description":"ktfio.walkTopDown","location":"ktfio/ktfio/walk-top-down.html","searchKeys":["walkTopDown","fun File.walkTopDown(): FileTreeWalk","ktfio.walkTopDown"]},{"name":"fun FileIOException(fileName: String, reason: String)","description":"ktfio.FileIOException.FileIOException","location":"ktfio/ktfio/-file-i-o-exception/-file-i-o-exception.html","searchKeys":["FileIOException","fun FileIOException(fileName: String, reason: String)","ktfio.FileIOException.FileIOException"]},{"name":"fun FileNotFoundException(fileName: String, reason: String)","description":"ktfio.FileNotFoundException.FileNotFoundException","location":"ktfio/ktfio/-file-not-found-exception/-file-not-found-exception.html","searchKeys":["FileNotFoundException","fun FileNotFoundException(fileName: String, reason: String)","ktfio.FileNotFoundException.FileNotFoundException"]},{"name":"fun IllegalFileAccess(fileName: String, reason: String)","description":"ktfio.IllegalFileAccess.IllegalFileAccess","location":"ktfio/ktfio/-illegal-file-access/-illegal-file-access.html","searchKeys":["IllegalFileAccess","fun IllegalFileAccess(fileName: String, reason: String)","ktfio.IllegalFileAccess.IllegalFileAccess"]},{"name":"fun maxDepth(depth: Int): FileTreeWalk","description":"ktfio.FileTreeWalk.maxDepth","location":"ktfio/ktfio/-file-tree-walk/max-depth.html","searchKeys":["maxDepth","fun maxDepth(depth: Int): FileTreeWalk","ktfio.FileTreeWalk.maxDepth"]},{"name":"fun onEnter(function: (File) -> Boolean): FileTreeWalk","description":"ktfio.FileTreeWalk.onEnter","location":"ktfio/ktfio/-file-tree-walk/on-enter.html","searchKeys":["onEnter","fun onEnter(function: (File) -> Boolean): FileTreeWalk","ktfio.FileTreeWalk.onEnter"]},{"name":"fun onFail(function: (File, FileIOException) -> Unit): FileTreeWalk","description":"ktfio.FileTreeWalk.onFail","location":"ktfio/ktfio/-file-tree-walk/on-fail.html","searchKeys":["onFail","fun onFail(function: (File, FileIOException) -> Unit): FileTreeWalk","ktfio.FileTreeWalk.onFail"]},{"name":"fun onLeave(function: (File) -> Unit): FileTreeWalk","description":"ktfio.FileTreeWalk.onLeave","location":"ktfio/ktfio/-file-tree-walk/on-leave.html","searchKeys":["onLeave","fun onLeave(function: (File) -> Unit): FileTreeWalk","ktfio.FileTreeWalk.onLeave"]},{"name":"inline fun Int.ensureUnixCallResult(op: String, predicate: (Int) -> Boolean): Int","description":"ktfio.ensureUnixCallResult","location":"ktfio/ktfio/ensure-unix-call-result.html","searchKeys":["ensureUnixCallResult","inline fun Int.ensureUnixCallResult(op: String, predicate: (Int) -> Boolean): Int","ktfio.ensureUnixCallResult"]},{"name":"inline fun Long.ensureUnixCallResult(op: String, predicate: (Long) -> Boolean): Long","description":"ktfio.ensureUnixCallResult","location":"ktfio/ktfio/ensure-unix-call-result.html","searchKeys":["ensureUnixCallResult","inline fun Long.ensureUnixCallResult(op: String, predicate: (Long) -> Boolean): Long","ktfio.ensureUnixCallResult"]},{"name":"inline fun ULong.ensureUnixCallResult(op: String, predicate: (ULong) -> Boolean): ULong","description":"ktfio.ensureUnixCallResult","location":"ktfio/ktfio/ensure-unix-call-result.html","searchKeys":["ensureUnixCallResult","inline fun ULong.ensureUnixCallResult(op: String, predicate: (ULong) -> Boolean): ULong","ktfio.ensureUnixCallResult"]},{"name":"open class FileIOException(fileName: String, reason: String) : Exception","description":"ktfio.FileIOException","location":"ktfio/ktfio/-file-i-o-exception/index.html","searchKeys":["FileIOException","open class FileIOException(fileName: String, reason: String) : Exception","ktfio.FileIOException"]},{"name":"open operator override fun iterator(): Iterator<File>","description":"ktfio.FileTreeWalk.iterator","location":"ktfio/ktfio/-file-tree-walk/iterator.html","searchKeys":["iterator","open operator override fun iterator(): Iterator<File>","ktfio.FileTreeWalk.iterator"]},{"name":"open override fun toString(): String","description":"ktfio.File.toString","location":"ktfio/ktfio/-file/[mingw-x64]to-string.html","searchKeys":["toString","open override fun toString(): String","ktfio.File.toString"]},{"name":"open override fun toString(): String","description":"ktfio.File.toString","location":"ktfio/ktfio/-file/[posix]to-string.html","searchKeys":["toString","open override fun toString(): String","ktfio.File.toString"]},{"name":"val File.nameWithoutExtension: String","description":"ktfio.nameWithoutExtension","location":"ktfio/ktfio/name-without-extension.html","searchKeys":["nameWithoutExtension","val File.nameWithoutExtension: String","ktfio.nameWithoutExtension"]}]
